.gitignore
AUTHORS
COPYING
ChangeLog
MANIFEST.in
README.md
TRANSLATORS
launcher
resources.qrc
setup.py
bin/ffconverter
ffconverter/__init__.py
ffconverter/about_dlg.py
ffconverter/audiovideotab.py
ffconverter/config.py
ffconverter/dynamictab.py
ffconverter/ffconverter.py
ffconverter/imagetab.py
ffconverter/preferences_dlg.py
ffconverter/presets_dlgs.py
ffconverter/progress.py
ffconverter/qrc_resources.py
ffconverter/utils.py
ffconverter.egg-info/PKG-INFO
ffconverter.egg-info/SOURCES.txt
ffconverter.egg-info/dependency_links.txt
ffconverter.egg-info/top_level.txt
locale/ffconverter.pro
locale/ffconverter_bg.ts
locale/ffconverter_ca.ts
locale/ffconverter_cs.ts
locale/ffconverter_de_DE.ts
locale/ffconverter_el.ts
locale/ffconverter_en.ts
locale/ffconverter_es.ts
locale/ffconverter_fr.ts
locale/ffconverter_gl.ts
locale/ffconverter_gl_ES.ts
locale/ffconverter_hu.ts
locale/ffconverter_it.ts
locale/ffconverter_ms_MY.ts
locale/ffconverter_pl_PL.ts
locale/ffconverter_pt.ts
locale/ffconverter_pt_BR.ts
locale/ffconverter_ro_RO.ts
locale/ffconverter_ru.ts
locale/ffconverter_tr.ts
locale/ffconverter_vi.ts
locale/ffconverter_zh_CN.ts
locale/ffconverter_zh_TW.ts
man/ffconverter.1.gz
share/ffconverter.desktop
share/ffconverter.png
share/presets.xml
test/test_dialogs.py